fast_query_parsers-1.0.3.dist-info/METADATA
fast_query_parsers-1.0.3.dist-info/WHEEL
fast_query_parsers-1.0.3.dist-info/license_files/LICENSE
fast_query_parsers/__init__.py
fast_query_parsers/__init__.pyi
fast_query_parsers/py.typed
fast_query_parsers/fast_query_parsers.abi3.so
fast_query_parsers-1.0.3.dist-info/RECORD
