Metadata-Version: 2.1
Name: fast-query-parsers
Version: 1.0.3
Classifier: Development Status :: 5 - Production/Stable
Classifier: Environment :: Web Environment
Classifier: License :: OSI Approved :: MIT License
Classifier: Natural Language :: English
Classifier: Operating System :: OS Independent
Classifier: Programming Language :: Python :: 3.8
Classifier: Programming Language :: Python :: 3.9
Classifier: Programming Language :: Python :: 3.10
Classifier: Programming Language :: Python :: 3.11
Classifier: Programming Language :: Python :: Implementation :: CPython
Classifier: Programming Language :: Python
Classifier: Programming Language :: Rust
Classifier: Topic :: Internet :: WWW/HTTP
Classifier: Topic :: Software Development :: Libraries
Classifier: Topic :: Software Development
Classifier: Typing :: Typed
License-File: LICENSE
Summary: Ultra-fast query string and url-encoded form-data parsers
Keywords: query,query string,qs,query parameters,rust,asgi,starlite,litestar,parser
Author: Na'aman Hirschfeld <nhirschfeld@gmail.com>
Author-email: Na'aman Hirschfeld <nhirschfeld@gmail.com>
Requires-Python: >=3.8
Project-URL: Source Code, https://github.com/starlite-api/fast-query-parsers
